{"cameraMode":{"drawMode":0,"name":"Shaded","section":"Shading Mode"},"sceneLighting":false,"audioPlay":false,"sceneViewState":{"showFog":true,"showMaterialUpdate":false,"showSkybox":false,"showFlares":true,"showImageEffects":true,"showParticleSystems":true},"in2DMode":false,"pivot":{"x":-5.918054103851318,"y":-4.58723258972168,"z":-0.11939620971679688},"rotation":{"x":0.2297738939523697,"y":0.20577166974544526,"z":-0.049754612147808078,"w":0.9499839544296265},"size":2.3237485885620119,"orthographic":false}